LICENSE
MANIFEST.in
README.md
requirements.txt
setup.py
django_userproperty.egg-info/PKG-INFO
django_userproperty.egg-info/SOURCES.txt
django_userproperty.egg-info/dependency_links.txt
django_userproperty.egg-info/requires.txt
django_userproperty.egg-info/top_level.txt
userproperty/__init__.py
userproperty/admin.py
userproperty/models.py
userproperty/urls.py
userproperty/utils.py
userproperty/views.py
userproperty/migrations/0001_initial.py
userproperty/migrations/__init__.py
userproperty/templatetags/__init__.py
userproperty/templatetags/userproperty_tags.py