Metadata-Version: 1.0
Name: django-userproperty
Version: 1.0.8
Summary: django userproperty
Home-page: UNKNOWN
Author: arteria GmbH
Author-email: admin@arteria.ch
License: BSD
Platform: UNKNOWN
